{
  "start_date": "2026-03-10",
  "portfolios": {
    "conservative": {
      "total_days": 5,
      "initial_value": 2000000.0,
      "current_value": 2000000.0,
      "peak_value": 2000000.0,
      "total_return_pct": 0.0,
      "max_drawdown_pct": 0.0,
      "sharpe_ratio": 0
    },
    "experimental": {
      "total_days": 5,
      "initial_value": 2000000.0,
      "current_value": 2000000.0,
      "peak_value": 2000000.0,
      "total_return_pct": 0.0,
      "max_drawdown_pct": 0.0,
      "sharpe_ratio": 0
    }
  },
  "daily": [
    {
      "date": "2026-03-10",
      "conservative": {
        "total_value": 2000000.0,
        "cash": 2000000.0,
        "n_positions": 0
      },
      "experimental": {
        "total_value": 2000000.0,
        "cash": 2000000.0,
        "n_positions": 0
      }
    },
    {
      "date": "2026-03-11",
      "conservative": {
        "total_value": 2000000.0,
        "cash": 2000000.0,
        "n_positions": 0
      },
      "experimental": {
        "total_value": 2000000.0,
        "cash": 2000000.0,
        "n_positions": 0
      }
    },
    {
      "date": "2026-03-12",
      "conservative": {
        "total_value": 2000000.0,
        "cash": 2000000.0,
        "n_positions": 0
      },
      "experimental": {
        "total_value": 2000000.0,
        "cash": 2000000.0,
        "n_positions": 0
      }
    },
    {
      "date": "2026-03-13",
      "conservative": {
        "total_value": 2000000.0,
        "cash": 2000000.0,
        "n_positions": 0
      },
      "experimental": {
        "total_value": 2000000.0,
        "cash": 2000000.0,
        "n_positions": 0
      }
    },
    {
      "date": "2026-03-16",
      "conservative": {
        "total_value": 2000000.0,
        "cash": 2000000.0,
        "n_positions": 0
      },
      "experimental": {
        "total_value": 2000000.0,
        "cash": 2000000.0,
        "n_positions": 0
      }
    }
  ],
  "last_updated": "2026-03-16"
}